{
  "apiVersion": "dashboard.grafana.app/v0alpha1",
  "kind": "Dashboard",
  "metadata": {
    "annotations": {
      "grafana.app/folder": "cdl4fwl71924gc"
    },
    "labels": {},
    "name": "vSaPgcFMk",
    "namespace": "stacks-660328"
  },
  "spec": {
    "annotations": {
      "list": [
        {
          "builtIn": 1,
          "datasource": {
            "type": "datasource",
            "uid": "grafana"
          },
          "enable": true,
          "hide": true,
          "iconColor": "rgba(0, 211, 255, 1)",
          "name": "Annotations \u0026 Alerts",
          "type": "dashboard"
        }
      ]
    },
    "editable": true,
    "fiscalYearStartMonth": 0,
    "graphTooltip": 0,
    "links": [
      {
        "asDropdown": false,
        "icon": "external link",
        "includeVars": false,
        "keepTime": false,
        "tags": [],
        "targetBlank": true,
        "title": "Miniflux",
        "tooltip": "",
        "type": "link",
        "url": "https://rss.kevingomez.fr/unread"
      }
    ],
    "panels": [
      {
        "collapsed": false,
        "gridPos": {
          "h": 1,
          "w": 24,
          "x": 0,
          "y": 0
        },
        "id": 24,
        "panels": [],
        "title": "Application",
        "type": "row"
      },
      {
        "datasource": {
          "type": "prometheus",
          "uid": "grafanacloud-prom"
        },
        "fieldConfig": {
          "defaults": {
            "mappings": [],
            "thresholds": {
              "mode": "absolute",
              "steps": [
                {
                  "color": "green",
                  "value": null
                }
              ]
            }
          },
          "overrides": []
        },
        "gridPos": {
          "h": 5,
          "w": 8,
          "x": 0,
          "y": 1
        },
        "id": 18,
        "options": {
          "displayMode": "basic",
          "legend": {
            "calcs": [],
            "displayMode": "list",
            "placement": "bottom",
            "showLegend": false
          },
          "maxVizHeight": 300,
          "minVizHeight": 16,
          "minVizWidth": 8,
          "namePlacement": "auto",
          "orientation": "horizontal",
          "reduceOptions": {
            "calcs": [
              "last"
            ],
            "fields": "",
            "values": false
          },
          "showUnfilled": true,
          "sizing": "auto",
          "valueMode": "color"
        },
        "pluginVersion": "11.4.0-78571",
        "targets": [
          {
            "datasource": {
              "type": "prometheus",
              "uid": "grafanacloud-prom"
            },
            "editorMode": "code",
            "expr": "max(miniflux_feeds{status=\"total\"})",
            "hide": false,
            "interval": "",
            "legendFormat": "Total",
            "range": true,
            "refId": "D"
          },
          {
            "datasource": {
              "type": "prometheus",
              "uid": "grafanacloud-prom"
            },
            "expr": "max(miniflux_feeds{status=\"enabled\"})",
            "hide": false,
            "interval": "",
            "legendFormat": "Enabled",
            "refId": "C"
          },
          {
            "datasource": {
              "type": "prometheus",
              "uid": "grafanacloud-prom"
            },
            "expr": "max(miniflux_broken_feeds)",
            "interval": "",
            "legendFormat": "Broken",
            "refId": "A"
          },
          {
            "datasource": {
              "type": "prometheus",
              "uid": "grafanacloud-prom"
            },
            "expr": "max(miniflux_feeds{status=\"disabled\"})",
            "interval": "",
            "legendFormat": "Disabled",
            "refId": "B"
          }
        ],
        "title": "Feeds",
        "type": "bargauge"
      },
      {
        "datasource": {
          "type": "prometheus",
          "uid": "grafanacloud-prom"
        },
        "fieldConfig": {
          "defaults": {
            "mappings": [],
            "thresholds": {
              "mode": "absolute",
              "steps": [
                {
                  "color": "green",
                  "value": null
                },
                {
                  "color": "red",
                  "value": 80
                }
              ]
            }
          },
          "overrides": []
        },
        "gridPos": {
          "h": 3,
          "w": 4,
          "x": 8,
          "y": 1
        },
        "id": 2,
        "options": {
          "colorMode": "value",
          "graphMode": "none",
          "justifyMode": "auto",
          "orientation": "horizontal",
          "percentChangeColorMode": "standard",
          "reduceOptions": {
            "calcs": [
              "last"
            ],
            "fields": "",
            "values": false
          },
          "showPercentChange": false,
          "textMode": "auto",
          "wideLayout": true
        },
        "pluginVersion": "11.4.0-78571",
        "targets": [
          {
            "datasource": {
              "type": "prometheus",
              "uid": "grafanacloud-prom"
            },
            "expr": "max(miniflux_users)",
            "interval": "",
            "legendFormat": "Users",
            "refId": "A"
          }
        ],
        "title": "Users",
        "type": "stat"
      },
      {
        "datasource": {
          "type": "prometheus",
          "uid": "grafanacloud-prom"
        },
        "fieldConfig": {
          "defaults": {
            "color": {
              "fixedColor": "green",
              "mode": "thresholds"
            },
            "mappings": [],
            "thresholds": {
              "mode": "absolute",
              "steps": [
                {
                  "color": "green",
                  "value": null
                }
              ]
            },
            "unit": "short"
          },
          "overrides": []
        },
        "gridPos": {
          "h": 5,
          "w": 8,
          "x": 12,
          "y": 1
        },
        "id": 4,
        "options": {
          "displayMode": "basic",
          "legend": {
            "calcs": [],
            "displayMode": "list",
            "placement": "bottom",
            "showLegend": false
          },
          "maxVizHeight": 300,
          "minVizHeight": 16,
          "minVizWidth": 8,
          "namePlacement": "auto",
          "orientation": "horizontal",
          "reduceOptions": {
            "calcs": [
              "lastNotNull"
            ],
            "fields": "",
            "values": false
          },
          "showUnfilled": true,
          "sizing": "auto",
          "valueMode": "color"
        },
        "pluginVersion": "11.4.0-78571",
        "targets": [
          {
            "datasource": {
              "type": "prometheus",
              "uid": "grafanacloud-prom"
            },
            "editorMode": "code",
            "expr": "max(miniflux_entries{status=\"total\"})",
            "hide": false,
            "interval": "",
            "legendFormat": "Total",
            "range": true,
            "refId": "A"
          },
          {
            "datasource": {
              "type": "prometheus",
              "uid": "grafanacloud-prom"
            },
            "expr": "max(miniflux_entries{status=\"unread\"})",
            "hide": false,
            "interval": "",
            "legendFormat": "Unread",
            "refId": "B"
          },
          {
            "datasource": {
              "type": "prometheus",
              "uid": "grafanacloud-prom"
            },
            "expr": "max(miniflux_entries{status=\"read\"})",
            "interval": "",
            "legendFormat": "Read",
            "refId": "C"
          },
          {
            "datasource": {
              "type": "prometheus",
              "uid": "grafanacloud-prom"
            },
            "expr": "max(miniflux_entries{status=\"removed\"})",
            "interval": "",
            "legendFormat": "Removed",
            "refId": "D"
          }
        ],
        "title": "Entries by Status",
        "type": "bargauge"
      },
      {
        "datasource": {
          "type": "prometheus",
          "uid": "${DS_PROMETHEUS}"
        },
        "fieldConfig": {
          "defaults": {
            "color": {
              "mode": "thresholds"
            },
            "mappings": [],
            "thresholds": {
              "mode": "absolute",
              "steps": [
                {
                  "color": "green",
                  "value": null
                },
                {
                  "color": "yellow",
                  "value": 80
                },
                {
                  "color": "orange",
                  "value": 160
                },
                {
                  "color": "red",
                  "value": 240
                }
              ]
            },
            "unit": "short"
          },
          "overrides": []
        },
        "gridPos": {
          "h": 5,
          "w": 4,
          "x": 20,
          "y": 1
        },
        "id": 37,
        "links": [
          {
            "targetBlank": true,
            "title": "Unread entries",
            "url": "https://rss.kevingomez.fr/unread"
          }
        ],
        "options": {
          "colorMode": "value",
          "graphMode": "area",
          "justifyMode": "auto",
          "orientation": "auto",
          "percentChangeColorMode": "standard",
          "reduceOptions": {
            "calcs": [
              "lastNotNull"
            ],
            "fields": "",
            "values": false
          },
          "showPercentChange": false,
          "textMode": "auto",
          "wideLayout": true
        },
        "pluginVersion": "11.4.0-78571",
        "targets": [
          {
            "datasource": {
              "type": "prometheus",
              "uid": "${DS_PROMETHEUS}"
            },
            "editorMode": "code",
            "exemplar": false,
            "expr": "max(miniflux_entries{status=\"unread\"})",
            "hide": false,
            "instant": true,
            "legendFormat": "__auto",
            "range": false,
            "refId": "A"
          }
        ],
        "title": "Unread",
        "type": "stat"
      },
      {
        "datasource": {
          "type": "prometheus",
          "uid": "grafanacloud-prom"
        },
        "description": "",
        "fieldConfig": {
          "defaults": {
            "mappings": [],
            "thresholds": {
              "mode": "absolute",
              "steps": [
                {
                  "color": "green",
                  "value": null
                }
              ]
            },
            "unit": "decbytes"
          },
          "overrides": []
        },
        "gridPos": {
          "h": 2,
          "w": 4,
          "x": 8,
          "y": 4
        },
        "id": 36,
        "options": {
          "colorMode": "value",
          "graphMode": "none",
          "justifyMode": "center",
          "orientation": "vertical",
          "percentChangeColorMode": "standard",
          "reduceOptions": {
            "calcs": [
              "last"
            ],
            "fields": "",
            "values": false
          },
          "showPercentChange": false,
          "textMode": "value",
          "wideLayout": true
        },
        "pluginVersion": "11.4.0-78571",
        "targets": [
          {
            "datasource": {
              "type": "prometheus",
              "uid": "grafanacloud-prom"
            },
            "expr": "go_memstats_sys_bytes{job=\"miniflux\"}",
            "interval": "",
            "legendFormat": "{{ instance }} - Memory Used",
            "refId": "A"
          }
        ],
        "title": "",
        "type": "stat"
      },
      {
        "datasource": {
          "type": "yesoreyeram-infinity-datasource",
          "uid": "ee3dadj941mgwf"
        },
        "fieldConfig": {
          "defaults": {
            "color": {
              "mode": "thresholds"
            },
            "custom": {
              "align": "auto",
              "cellOptions": {
                "type": "auto",
                "wrapText": false
              },
              "inspect": false
            },
            "links": [],
            "mappings": [],
            "thresholds": {
              "mode": "absolute",
              "steps": [
                {
                  "color": "green",
                  "value": null
                },
                {
                  "color": "red",
                  "value": 80
                }
              ]
            }
          },
          "overrides": [
            {
              "matcher": {
                "id": "byName",
                "options": "ID"
              },
              "properties": [
                {
                  "id": "custom.hidden",
                  "value": true
                }
              ]
            },
            {
              "matcher": {
                "id": "byName",
                "options": "Title"
              },
              "properties": [
                {
                  "id": "links",
                  "value": [
                    {
                      "targetBlank": true,
                      "title": "Read",
                      "url": "https://rss.kevingomez.fr/unread/entry/${__data.fields.ID}"
                    }
                  ]
                }
              ]
            },
            {
              "matcher": {
                "id": "byName",
                "options": "Published"
              },
              "properties": [
                {
                  "id": "unit",
                  "value": "dateTimeFromNow"
                },
                {
                  "id": "custom.width",
                  "value": 150
                }
              ]
            },
            {
              "matcher": {
                "id": "byName",
                "options": "Category"
              },
              "properties": [
                {
                  "id": "custom.width",
                  "value": 200
                }
              ]
            }
          ]
        },
        "gridPos": {
          "h": 10,
          "w": 24,
          "x": 0,
          "y": 6
        },
        "id": 38,
        "links": [
          {
            "targetBlank": true,
            "title": "Unread entries",
            "url": "https://rss.kevingomez.fr/unread"
          }
        ],
        "options": {
          "cellHeight": "sm",
          "footer": {
            "countRows": false,
            "enablePagination": true,
            "fields": "",
            "reducer": [
              "sum"
            ],
            "show": false
          },
          "showHeader": true
        },
        "pluginVersion": "11.4.0-78571",
        "targets": [
          {
            "columns": [
              {
                "selector": "feed.category.title",
                "text": "Category",
                "type": "string"
              },
              {
                "selector": "feed.title",
                "text": "Feed",
                "type": "string"
              },
              {
                "selector": "title",
                "text": "Title",
                "type": "string"
              },
              {
                "selector": "published_at",
                "text": "Published",
                "timestampFormat": "",
                "type": "timestamp"
              },
              {
                "selector": "id",
                "text": "ID",
                "type": "string"
              }
            ],
            "computed_columns": [
              {
                "selector": "feed.title + feed.category.title",
                "text": "",
                "type": "string"
              }
            ],
            "datasource": {
              "type": "yesoreyeram-infinity-datasource",
              "uid": "ee3dadj941mgwf"
            },
            "filters": [],
            "format": "logs",
            "global_query_id": "",
            "json_options": {
              "columnar": false
            },
            "parser": "simple",
            "refId": "A",
            "root_selector": "entries",
            "source": "url",
            "type": "json",
            "url": "https://rss.kevingomez.fr/v1/entries?status=unread\u0026direction=desc",
            "url_options": {
              "data": "",
              "method": "GET"
            }
          }
        ],
        "title": "Unread entries",
        "type": "table"
      },
      {
        "datasource": {
          "type": "prometheus",
          "uid": "grafanacloud-prom"
        },
        "fieldConfig": {
          "defaults": {
            "color": {
              "mode": "palette-classic"
            },
            "custom": {
              "axisBorderShow": false,
              "axisCenteredZero": false,
              "axisColorMode": "text",
              "axisLabel": "",
              "axisPlacement": "auto",
              "barAlignment": 0,
              "barWidthFactor": 0.6,
              "drawStyle": "line",
              "fillOpacity": 10,
              "gradientMode": "none",
              "hideFrom": {
                "legend": false,
                "tooltip": false,
                "viz": false
              },
              "insertNulls": false,
              "lineInterpolation": "linear",
              "lineWidth": 1,
              "pointSize": 5,
              "scaleDistribution": {
                "type": "linear"
              },
              "showPoints": "never",
              "spanNulls": false,
              "stacking": {
                "group": "A",
                "mode": "none"
              },
              "thresholdsStyle": {
                "mode": "off"
              }
            },
            "mappings": [],
            "thresholds": {
              "mode": "absolute",
              "steps": [
                {
                  "color": "green",
                  "value": null
                },
                {
                  "color": "red",
                  "value": 80
                }
              ]
            },
            "unit": "s"
          },
          "overrides": []
        },
        "gridPos": {
          "h": 7,
          "w": 12,
          "x": 0,
          "y": 16
        },
        "id": 22,
        "options": {
          "legend": {
            "calcs": [],
            "displayMode": "list",
            "placement": "bottom",
            "showLegend": true
          },
          "tooltip": {
            "mode": "multi",
            "sort": "none"
          }
        },
        "pluginVersion": "11.4.0-78571",
        "targets": [
          {
            "datasource": {
              "type": "prometheus",
              "uid": "grafanacloud-prom"
            },
            "editorMode": "code",
            "expr": "histogram_quantile(0.95, sum(rate(miniflux_scraper_request_duration_bucket[5m])) by (le))",
            "interval": "",
            "legendFormat": "Request Duration",
            "range": true,
            "refId": "A"
          }
        ],
        "title": "Scraper Request Duration",
        "type": "timeseries"
      },
      {
        "datasource": {
          "type": "prometheus",
          "uid": "grafanacloud-prom"
        },
        "fieldConfig": {
          "defaults": {
            "color": {
              "mode": "palette-classic"
            },
            "custom": {
              "axisBorderShow": false,
              "axisCenteredZero": false,
              "axisColorMode": "text",
              "axisLabel": "",
              "axisPlacement": "auto",
              "barAlignment": 0,
              "barWidthFactor": 0.6,
              "drawStyle": "line",
              "fillOpacity": 10,
              "gradientMode": "none",
              "hideFrom": {
                "legend": false,
                "tooltip": false,
                "viz": false
              },
              "insertNulls": false,
              "lineInterpolation": "linear",
              "lineWidth": 1,
              "pointSize": 5,
              "scaleDistribution": {
                "type": "linear"
              },
              "showPoints": "never",
              "spanNulls": false,
              "stacking": {
                "group": "A",
                "mode": "none"
              },
              "thresholdsStyle": {
                "mode": "off"
              }
            },
            "mappings": [],
            "thresholds": {
              "mode": "absolute",
              "steps": [
                {
                  "color": "green",
                  "value": null
                },
                {
                  "color": "red",
                  "value": 80
                }
              ]
            },
            "unit": "s"
          },
          "overrides": []
        },
        "gridPos": {
          "h": 7,
          "w": 12,
          "x": 12,
          "y": 16
        },
        "id": 20,
        "options": {
          "legend": {
            "calcs": [],
            "displayMode": "list",
            "placement": "bottom",
            "showLegend": true
          },
          "tooltip": {
            "mode": "multi",
            "sort": "none"
          }
        },
        "pluginVersion": "11.4.0-78571",
        "targets": [
          {
            "datasource": {
              "type": "prometheus",
              "uid": "grafanacloud-prom"
            },
            "editorMode": "code",
            "expr": "histogram_quantile(0.95, sum(rate(miniflux_background_feed_refresh_duration_bucket[5m])) by (le))",
            "interval": "",
            "legendFormat": "Refresh Duration",
            "range": true,
            "refId": "A"
          }
        ],
        "title": "Background Feed Refresh Duration",
        "type": "timeseries"
      },
      {
        "collapsed": false,
        "gridPos": {
          "h": 1,
          "w": 24,
          "x": 0,
          "y": 23
        },
        "id": 28,
        "panels": [],
        "title": "Process",
        "type": "row"
      },
      {
        "datasource": {
          "type": "prometheus",
          "uid": "grafanacloud-prom"
        },
        "fieldConfig": {
          "defaults": {
            "color": {
              "mode": "palette-classic"
            },
            "custom": {
              "axisBorderShow": false,
              "axisCenteredZero": false,
              "axisColorMode": "text",
              "axisLabel": "",
              "axisPlacement": "auto",
              "barAlignment": 0,
              "barWidthFactor": 0.6,
              "drawStyle": "line",
              "fillOpacity": 10,
              "gradientMode": "none",
              "hideFrom": {
                "legend": false,
                "tooltip": false,
                "viz": false
              },
              "insertNulls": false,
              "lineInterpolation": "linear",
              "lineWidth": 1,
              "pointSize": 5,
              "scaleDistribution": {
                "type": "linear"
              },
              "showPoints": "never",
              "spanNulls": false,
              "stacking": {
                "group": "A",
                "mode": "none"
              },
              "thresholdsStyle": {
                "mode": "off"
              }
            },
            "links": [],
            "mappings": [],
            "thresholds": {
              "mode": "absolute",
              "steps": [
                {
                  "color": "green",
                  "value": null
                },
                {
                  "color": "red",
                  "value": 80
                }
              ]
            },
            "unit": "decbytes"
          },
          "overrides": []
        },
        "gridPos": {
          "h": 8,
          "w": 12,
          "x": 0,
          "y": 24
        },
        "id": 16,
        "options": {
          "legend": {
            "calcs": [
              "lastNotNull"
            ],
            "displayMode": "table",
            "placement": "bottom",
            "showLegend": true
          },
          "tooltip": {
            "mode": "multi",
            "sort": "none"
          }
        },
        "pluginVersion": "11.4.0-78571",
        "targets": [
          {
            "datasource": {
              "type": "prometheus",
              "uid": "grafanacloud-prom"
            },
            "expr": "go_memstats_sys_bytes{job=\"miniflux\"}",
            "format": "time_series",
            "interval": "",
            "intervalFactor": 1,
            "legendFormat": "{{ instance }}",
            "refId": "A"
          }
        ],
        "title": "Total Used Memory",
        "type": "timeseries"
      },
      {
        "datasource": {
          "type": "prometheus",
          "uid": "grafanacloud-prom"
        },
        "fieldConfig": {
          "defaults": {
            "color": {
              "mode": "palette-classic"
            },
            "custom": {
              "axisBorderShow": false,
              "axisCenteredZero": false,
              "axisColorMode": "text",
              "axisLabel": "",
              "axisPlacement": "auto",
              "barAlignment": 0,
              "barWidthFactor": 0.6,
              "drawStyle": "line",
              "fillOpacity": 10,
              "gradientMode": "none",
              "hideFrom": {
                "legend": false,
                "tooltip": false,
                "viz": false
              },
              "insertNulls": false,
              "lineInterpolation": "linear",
              "lineWidth": 1,
              "pointSize": 5,
              "scaleDistribution": {
                "type": "linear"
              },
              "showPoints": "never",
              "spanNulls": false,
              "stacking": {
                "group": "A",
                "mode": "none"
              },
              "thresholdsStyle": {
                "mode": "off"
              }
            },
            "mappings": [],
            "thresholds": {
              "mode": "absolute",
              "steps": [
                {
                  "color": "green",
                  "value": null
                },
                {
                  "color": "red",
                  "value": 80
                }
              ]
            },
            "unit": "short"
          },
          "overrides": []
        },
        "gridPos": {
          "h": 8,
          "w": 12,
          "x": 12,
          "y": 24
        },
        "id": 6,
        "options": {
          "legend": {
            "calcs": [
              "mean",
              "lastNotNull",
              "max",
              "min"
            ],
            "displayMode": "table",
            "placement": "bottom",
            "showLegend": true
          },
          "tooltip": {
            "mode": "multi",
            "sort": "none"
          }
        },
        "pluginVersion": "11.4.0-78571",
        "targets": [
          {
            "datasource": {
              "type": "prometheus",
              "uid": "grafanacloud-prom"
            },
            "expr": "process_open_fds{job=\"miniflux\"}",
            "interval": "",
            "legendFormat": "{{instance }} - Open File Descriptors",
            "refId": "A"
          }
        ],
        "title": "File Descriptors",
        "type": "timeseries"
      },
      {
        "collapsed": false,
        "gridPos": {
          "h": 1,
          "w": 24,
          "x": 0,
          "y": 32
        },
        "id": 26,
        "panels": [],
        "title": "Go Metrics",
        "type": "row"
      },
      {
        "datasource": {
          "type": "prometheus",
          "uid": "grafanacloud-prom"
        },
        "fieldConfig": {
          "defaults": {
            "color": {
              "mode": "palette-classic"
            },
            "custom": {
              "axisBorderShow": false,
              "axisCenteredZero": false,
              "axisColorMode": "text",
              "axisLabel": "",
              "axisPlacement": "auto",
              "barAlignment": 0,
              "barWidthFactor": 0.6,
              "drawStyle": "line",
              "fillOpacity": 10,
              "gradientMode": "none",
              "hideFrom": {
                "legend": false,
                "tooltip": false,
                "viz": false
              },
              "insertNulls": false,
              "lineInterpolation": "linear",
              "lineWidth": 2,
              "pointSize": 5,
              "scaleDistribution": {
                "type": "linear"
              },
              "showPoints": "never",
              "spanNulls": true,
              "stacking": {
                "group": "A",
                "mode": "none"
              },
              "thresholdsStyle": {
                "mode": "off"
              }
            },
            "mappings": [],
            "thresholds": {
              "mode": "absolute",
              "steps": [
                {
                  "color": "green",
                  "value": null
                },
                {
                  "color": "red",
                  "value": 80
                }
              ]
            },
            "unit": "bytes"
          },
          "overrides": [
            {
              "matcher": {
                "id": "byName",
                "options": "alloc rate"
              },
              "properties": [
                {
                  "id": "unit",
                  "value": "Bps"
                }
              ]
            }
          ]
        },
        "gridPos": {
          "h": 7,
          "w": 8,
          "x": 0,
          "y": 33
        },
        "id": 12,
        "options": {
          "legend": {
            "calcs": [
              "mean",
              "lastNotNull",
              "max"
            ],
            "displayMode": "table",
            "placement": "bottom",
            "showLegend": true
          },
          "tooltip": {
            "mode": "multi",
            "sort": "none"
          }
        },
        "pluginVersion": "11.4.0-78571",
        "targets": [
          {
            "datasource": {
              "type": "prometheus",
              "uid": "grafanacloud-prom"
            },
            "expr": "go_memstats_alloc_bytes{job=\"miniflux\"}",
            "format": "time_series",
            "interval": "",
            "intervalFactor": 2,
            "legendFormat": "bytes allocated",
            "metric": "go_memstats_alloc_bytes",
            "refId": "A",
            "step": 4
          },
          {
            "datasource": {
              "type": "prometheus",
              "uid": "grafanacloud-prom"
            },
            "expr": "rate(go_memstats_alloc_bytes_total{job=\"miniflux\"}[30s])",
            "format": "time_series",
            "interval": "",
            "intervalFactor": 2,
            "legendFormat": "alloc rate",
            "metric": "go_memstats_alloc_bytes_total",
            "refId": "B",
            "step": 4
          },
          {
            "datasource": {
              "type": "prometheus",
              "uid": "grafanacloud-prom"
            },
            "expr": "go_memstats_stack_inuse_bytes{job=\"miniflux\"}",
            "format": "time_series",
            "interval": "",
            "intervalFactor": 2,
            "legendFormat": "stack inuse",
            "metric": "go_memstats_stack_inuse_bytes",
            "refId": "C",
            "step": 4
          },
          {
            "datasource": {
              "type": "prometheus",
              "uid": "grafanacloud-prom"
            },
            "expr": "go_memstats_heap_inuse_bytes{job=\"miniflux\"}",
            "format": "time_series",
            "hide": false,
            "interval": "",
            "intervalFactor": 2,
            "legendFormat": "heap inuse",
            "metric": "go_memstats_heap_inuse_bytes",
            "refId": "D",
            "step": 4
          }
        ],
        "title": "Golang Memory",
        "type": "timeseries"
      },
      {
        "datasource": {
          "type": "prometheus",
          "uid": "grafanacloud-prom"
        },
        "fieldConfig": {
          "defaults": {
            "color": {
              "mode": "palette-classic"
            },
            "custom": {
              "axisBorderShow": false,
              "axisCenteredZero": false,
              "axisColorMode": "text",
              "axisLabel": "",
              "axisPlacement": "auto",
              "barAlignment": 0,
              "barWidthFactor": 0.6,
              "drawStyle": "line",
              "fillOpacity": 10,
              "gradientMode": "none",
              "hideFrom": {
                "legend": false,
                "tooltip": false,
                "viz": false
              },
              "insertNulls": false,
              "lineInterpolation": "linear",
              "lineWidth": 1,
              "pointSize": 5,
              "scaleDistribution": {
                "type": "linear"
              },
              "showPoints": "never",
              "spanNulls": false,
              "stacking": {
                "group": "A",
                "mode": "none"
              },
              "thresholdsStyle": {
                "mode": "off"
              }
            },
            "mappings": [],
            "thresholds": {
              "mode": "absolute",
              "steps": [
                {
                  "color": "green",
                  "value": null
                },
                {
                  "color": "red",
                  "value": 80
                }
              ]
            },
            "unit": "short"
          },
          "overrides": []
        },
        "gridPos": {
          "h": 7,
          "w": 8,
          "x": 8,
          "y": 33
        },
        "id": 8,
        "options": {
          "legend": {
            "calcs": [
              "mean",
              "lastNotNull",
              "max",
              "min"
            ],
            "displayMode": "table",
            "placement": "bottom",
            "showLegend": true
          },
          "tooltip": {
            "mode": "multi",
            "sort": "none"
          }
        },
        "pluginVersion": "11.4.0-78571",
        "targets": [
          {
            "datasource": {
              "type": "prometheus",
              "uid": "grafanacloud-prom"
            },
            "expr": "go_goroutines{job=\"miniflux\"}",
            "interval": "",
            "legendFormat": "{{ instance }} - Goroutines",
            "refId": "A"
          },
          {
            "datasource": {
              "type": "prometheus",
              "uid": "grafanacloud-prom"
            },
            "expr": "go_threads{job=\"miniflux\"}",
            "interval": "",
            "legendFormat": "{{ instance }} - OS threads",
            "refId": "B"
          }
        ],
        "title": "Concurrency",
        "type": "timeseries"
      },
      {
        "datasource": {
          "type": "prometheus",
          "uid": "grafanacloud-prom"
        },
        "fieldConfig": {
          "defaults": {
            "color": {
              "mode": "palette-classic"
            },
            "custom": {
              "axisBorderShow": false,
              "axisCenteredZero": false,
              "axisColorMode": "text",
              "axisLabel": "",
              "axisPlacement": "auto",
              "barAlignment": 0,
              "barWidthFactor": 0.6,
              "drawStyle": "line",
              "fillOpacity": 10,
              "gradientMode": "none",
              "hideFrom": {
                "legend": false,
                "tooltip": false,
                "viz": false
              },
              "insertNulls": false,
              "lineInterpolation": "linear",
              "lineWidth": 1,
              "pointSize": 5,
              "scaleDistribution": {
                "type": "linear"
              },
              "showPoints": "never",
              "spanNulls": false,
              "stacking": {
                "group": "A",
                "mode": "none"
              },
              "thresholdsStyle": {
                "mode": "off"
              }
            },
            "links": [],
            "mappings": [],
            "thresholds": {
              "mode": "absolute",
              "steps": [
                {
                  "color": "green",
                  "value": null
                },
                {
                  "color": "red",
                  "value": 80
                }
              ]
            },
            "unit": "short"
          },
          "overrides": []
        },
        "gridPos": {
          "h": 7,
          "w": 8,
          "x": 16,
          "y": 33
        },
        "id": 30,
        "options": {
          "legend": {
            "calcs": [],
            "displayMode": "list",
            "placement": "bottom",
            "showLegend": true
          },
          "tooltip": {
            "mode": "multi",
            "sort": "none"
          }
        },
        "pluginVersion": "11.4.0-78571",
        "targets": [
          {
            "datasource": {
              "type": "prometheus",
              "uid": "grafanacloud-prom"
            },
            "expr": "go_memstats_mallocs_total{job=\"miniflux\"} - go_memstats_frees_total{job=\"miniflux\"}",
            "format": "time_series",
            "interval": "",
            "intervalFactor": 1,
            "legendFormat": "{{ instance }}",
            "refId": "A"
          }
        ],
        "title": "Number of Live Objects",
        "type": "timeseries"
      },
      {
        "datasource": {
          "type": "prometheus",
          "uid": "grafanacloud-prom"
        },
        "fieldConfig": {
          "defaults": {
            "color": {
              "mode": "palette-classic"
            },
            "custom": {
              "axisBorderShow": false,
              "axisCenteredZero": false,
              "axisColorMode": "text",
              "axisLabel": "",
              "axisPlacement": "auto",
              "barAlignment": 0,
              "barWidthFactor": 0.6,
              "drawStyle": "line",
              "fillOpacity": 10,
              "gradientMode": "none",
              "hideFrom": {
                "legend": false,
                "tooltip": false,
                "viz": false
              },
              "insertNulls": false,
              "lineInterpolation": "linear",
              "lineWidth": 1,
              "pointSize": 5,
              "scaleDistribution": {
                "type": "linear"
              },
              "showPoints": "never",
              "spanNulls": false,
              "stacking": {
                "group": "A",
                "mode": "none"
              },
              "thresholdsStyle": {
                "mode": "off"
              }
            },
            "links": [],
            "mappings": [],
            "thresholds": {
              "mode": "absolute",
              "steps": [
                {
                  "color": "green",
                  "value": null
                },
                {
                  "color": "red",
                  "value": 80
                }
              ]
            },
            "unit": "decbytes"
          },
          "overrides": []
        },
        "gridPos": {
          "h": 8,
          "w": 8,
          "x": 0,
          "y": 40
        },
        "id": 34,
        "options": {
          "legend": {
            "calcs": [
              "lastNotNull"
            ],
            "displayMode": "table",
            "placement": "bottom",
            "showLegend": true
          },
          "tooltip": {
            "mode": "multi",
            "sort": "none"
          }
        },
        "pluginVersion": "11.4.0-78571",
        "targets": [
          {
            "datasource": {
              "type": "prometheus",
              "uid": "grafanacloud-prom"
            },
            "expr": "go_memstats_stack_inuse_bytes{job=\"miniflux\"}",
            "format": "time_series",
            "interval": "",
            "intervalFactor": 1,
            "legendFormat": "{{ instance }} - stack_inuse",
            "refId": "A"
          },
          {
            "datasource": {
              "type": "prometheus",
              "uid": "grafanacloud-prom"
            },
            "expr": "go_memstats_stack_sys_bytes{job=\"miniflux\"}",
            "format": "time_series",
            "interval": "",
            "intervalFactor": 1,
            "legendFormat": "{{ instance }} - stack_sys",
            "refId": "B"
          }
        ],
        "title": "Memory in Stack",
        "type": "timeseries"
      },
      {
        "datasource": {
          "type": "prometheus",
          "uid": "grafanacloud-prom"
        },
        "fieldConfig": {
          "defaults": {
            "color": {
              "mode": "palette-classic"
            },
            "custom": {
              "axisBorderShow": false,
              "axisCenteredZero": false,
              "axisColorMode": "text",
              "axisLabel": "",
              "axisPlacement": "auto",
              "barAlignment": 0,
              "barWidthFactor": 0.6,
              "drawStyle": "line",
              "fillOpacity": 10,
              "gradientMode": "none",
              "hideFrom": {
                "legend": false,
                "tooltip": false,
                "viz": false
              },
              "insertNulls": false,
              "lineInterpolation": "linear",
              "lineWidth": 1,
              "pointSize": 5,
              "scaleDistribution": {
                "type": "linear"
              },
              "showPoints": "never",
              "spanNulls": false,
              "stacking": {
                "group": "A",
                "mode": "none"
              },
              "thresholdsStyle": {
                "mode": "off"
              }
            },
            "links": [],
            "mappings": [],
            "thresholds": {
              "mode": "absolute",
              "steps": [
                {
                  "color": "green",
                  "value": null
                },
                {
                  "color": "red",
                  "value": 80
                }
              ]
            },
            "unit": "decbytes"
          },
          "overrides": []
        },
        "gridPos": {
          "h": 8,
          "w": 8,
          "x": 8,
          "y": 40
        },
        "id": 32,
        "options": {
          "legend": {
            "calcs": [],
            "displayMode": "list",
            "placement": "bottom",
            "showLegend": true
          },
          "tooltip": {
            "mode": "multi",
            "sort": "none"
          }
        },
        "pluginVersion": "11.4.0-78571",
        "targets": [
          {
            "datasource": {
              "type": "prometheus",
              "uid": "grafanacloud-prom"
            },
            "expr": "go_memstats_heap_alloc_bytes{job=\"miniflux\"}",
            "format": "time_series",
            "interval": "",
            "intervalFactor": 1,
            "legendFormat": "{{ instance }} - heap_alloc",
            "refId": "B"
          },
          {
            "datasource": {
              "type": "prometheus",
              "uid": "grafanacloud-prom"
            },
            "expr": "go_memstats_heap_sys_bytes{job=\"miniflux\"}",
            "format": "time_series",
            "interval": "",
            "intervalFactor": 1,
            "legendFormat": "{{ instance }} - heap_sys",
            "refId": "A"
          },
          {
            "datasource": {
              "type": "prometheus",
              "uid": "grafanacloud-prom"
            },
            "expr": "go_memstats_heap_idle_bytes{job=\"miniflux\"}",
            "format": "time_series",
            "interval": "",
            "intervalFactor": 1,
            "legendFormat": "{{ instance }} - heap_idle",
            "refId": "C"
          },
          {
            "datasource": {
              "type": "prometheus",
              "uid": "grafanacloud-prom"
            },
            "expr": "go_memstats_heap_inuse_bytes{job=\"miniflux\"}",
            "format": "time_series",
            "interval": "",
            "intervalFactor": 1,
            "legendFormat": "{{ instance }} - heap_inuse",
            "refId": "D"
          },
          {
            "datasource": {
              "type": "prometheus",
              "uid": "grafanacloud-prom"
            },
            "expr": "go_memstats_heap_released_bytes{job=\"miniflux\"}",
            "format": "time_series",
            "interval": "",
            "intervalFactor": 1,
            "legendFormat": "{{ instance }} - heap_released",
            "refId": "E"
          }
        ],
        "title": "Memory in Heap",
        "type": "timeseries"
      },
      {
        "datasource": {
          "type": "prometheus",
          "uid": "grafanacloud-prom"
        },
        "fieldConfig": {
          "defaults": {
            "color": {
              "mode": "palette-classic"
            },
            "custom": {
              "axisBorderShow": false,
              "axisCenteredZero": false,
              "axisColorMode": "text",
              "axisLabel": "",
              "axisPlacement": "auto",
              "barAlignment": 0,
              "barWidthFactor": 0.6,
              "drawStyle": "line",
              "fillOpacity": 10,
              "gradientMode": "none",
              "hideFrom": {
                "legend": false,
                "tooltip": false,
                "viz": false
              },
              "insertNulls": false,
              "lineInterpolation": "linear",
              "lineWidth": 2,
              "pointSize": 5,
              "scaleDistribution": {
                "type": "linear"
              },
              "showPoints": "never",
              "spanNulls": true,
              "stacking": {
                "group": "A",
                "mode": "none"
              },
              "thresholdsStyle": {
                "mode": "off"
              }
            },
            "mappings": [],
            "thresholds": {
              "mode": "absolute",
              "steps": [
                {
                  "color": "green",
                  "value": null
                },
                {
                  "color": "red",
                  "value": 80
                }
              ]
            },
            "unit": "s"
          },
          "overrides": []
        },
        "gridPos": {
          "h": 8,
          "w": 8,
          "x": 16,
          "y": 40
        },
        "id": 14,
        "options": {
          "legend": {
            "calcs": [
              "mean",
              "lastNotNull",
              "max"
            ],
            "displayMode": "table",
            "placement": "bottom",
            "showLegend": true
          },
          "tooltip": {
            "mode": "multi",
            "sort": "none"
          }
        },
        "pluginVersion": "11.4.0-78571",
        "targets": [
          {
            "datasource": {
              "type": "prometheus",
              "uid": "grafanacloud-prom"
            },
            "expr": "go_gc_duration_seconds{job=\"miniflux\"}",
            "format": "time_series",
            "interval": "",
            "intervalFactor": 2,
            "legendFormat": "{{instance}}: {{quantile}}",
            "metric": "go_gc_duration_seconds",
            "refId": "A",
            "step": 4
          }
        ],
        "title": "GC Duration Quantiles",
        "type": "timeseries"
      }
    ],
    "preload": false,
    "refresh": "30s",
    "schemaVersion": 40,
    "tags": [],
    "templating": {
      "list": [
        {
          "current": {
            "text": "grafanacloud-potatopi-prom",
            "value": "grafanacloud-prom"
          },
          "includeAll": false,
          "label": "Datasource",
          "name": "DS_PROMETHEUS",
          "options": [],
          "query": "prometheus",
          "refresh": 1,
          "regex": "",
          "type": "datasource"
        }
      ]
    },
    "time": {
      "from": "now-3h",
      "to": "now"
    },
    "timepicker": {},
    "timezone": "",
    "title": "Miniflux",
    "weekStart": ""
  }
}
